{
  "url": "https://pro.yandex.com/kz-kk/nur-sultan/knowledge-base/taxi/advice/two-child-seats",
  "domain": "pro.yandex.com",
  "locale": "kz-kk",
  "city": "nur-sultan",
  "hreflang": "kk-KZ",
  "category": "advice",
  "slug": "two-child-seats",
  "title": "Балалар креслосын жүксалғышқа қалай салу керек",
  "last_updated": "Соңғы жаңартпа 3 Mar 2025",
  "breadcrumbs": [
    "Білім базасы",
    "Сапарлар",
    "Пайдалы кеңестер"
  ],
  "content": "Балалар креслосын жүксалғышқа қалай салу керек\n\nСоңғы жаңартпа 3 Mar 2025\n\nRU KK\n\nҚарапайым машинаның жүксалғышына балалар креслосы мен бірнеше чемодан оңай сыйып кетеді. Бәрі сыйып тұратындай етіп заттарды қалай салу керектігін қараңыз.\n\nКейбір жүргізушілер балалар креслосының кесірінен жүксалғышқа ештеңе сыймайды деп санайды. Біз оның солай екенін тексермекші болып, танымал машина маркаларына барынша көп зат салып көрдік. Нәтижесінде, тіпті, Hyundai Solaris жүксалғышына екі чемодан мен балалар креслосын сыйғызуға болады екен. Бастысы — оларды ұқыптап салу.\n\nБір жүксалғышқа көп затты қалай сыйғызу керектігін қараңыз — өз моделіңізді немесе оған ұқсайтын машинаны таңдаңыз.\n\n⛔️ Төмендегі шешімдер ГБҚ орнатылған машиналарға жарамауы мүмкін. Бірақ, олар жүксалғышта орын үнемдеудің жалпы қағидаларын түсінуге көмектеседі.\n\nHyundai Solaris\n\nHyundai Solaris автокөлігіне екі чемодан мен балалар креслосын қалай салу керек\n\nRenault Logan\n\nRenault Logan автокөлігіне екі чемодан мен балалар креслосын қалай салу керек\n\nMercedes E-класса\n\nЕ-санатты Mercedes автокөлігіне екі чемодан мен балалар креслосын қалай салу керек\n\nМақала сіз үшін пайдалы болды ма?\n\nИә\n\nЖоқ\n\nКелесі мақала\n\nТапсырыстарды орындау үшін қандай автокөлік жарайды"
}