{
  "url": "https://pro.yandex.ru/ru-ru/moskva/knowledge-base/taxi/standards-check/ban",
  "domain": "pro.yandex.ru",
  "locale": "ru-ru",
  "city": "moskva",
  "hreflang": "ru-RU",
  "category": "standards-check",
  "slug": "ban",
  "title": "Когда могут ограничить доступ к заказам сервиса",
  "last_updated": "Последнее обновление 30 окт 2024",
  "breadcrumbs": [
    "База знаний",
    "Яндекс Такси",
    "Как проверяются стандарты"
  ],
  "content": "Когда могут ограничить доступ к заказам сервиса\n\nПоследнее обновление 30 окт 2024\n\nОграничение доступа может произойти автоматически — это делают алгоритмы сервиса по разным причинам. За однократное нарушение, сразу за несколько нарушений или же за регулярное несоблюдение правил. Вот самые частые причины, когда это происходит.\n\nПадение рейтинга\n\nЧтобы получать заказы сервиса, сейчас водителю нужен рейтинг не ниже 4.4.\n\nКакое ограничение. Если рейтинг водителя упадет ниже этого порога, доступ к заказам будет ограничен. Водители, у которых это впервые, могут временно вернуть доступ. У них будет возможность повысить рейтинг — выполнить до 150 заказов. Если и во время этих поездок рейтинг продолжит падать, доступ к сервису будет закрыт. Второй раз попробовать вернуть его можно будет через полгода.\n\nРейтинг\n\nСнижение приоритета за заказы\n\nКогда вы выполняете заказы без пропусков, приоритет за принятые заказы растёт. При пропусках и отменах приоритет за принятые заказы снижается. За отмены уже принятых заказов сгорает больше баллов приоритета, чем за пропуски.\n\nКакое ограничение. Если пропускать или отменять слишком много заказов, доступ к ним может быть ограничен на время. После этого можно будет вернуться на линию.\n\nПриоритет за принятые заказы\n\nОтклонение от стандартов\n\nАлгоритмы сервиса постоянно анализируют замечания пользователей о том, как водители выполняют стандарты. В повышенных тарифах процесс выполнения заказа проверяют ещё и тайные покупатели .\n\nКакое ограничение. Если отступление от стандартов незначительное, мы сообщим об этом водителю и дадим рекомендацию, как исправить ситуацию. Серьезное нарушение может привести к потере баллов приоритета, есть даже риск получить ограничение доступа к заказам.\n\nСтандарты «Эконома»\n\nСтандарты «Комфорта»\n\nСтандарты «Комфорта+»\n\nСтандарты «Детского»\n\nСтандарты «Минивэна»\n\nПравила премиальных тарифов Ultima\n\nСтандарты «Доставки» и «Курьера», если вы на автомобиле\n\nНарушение правил безопасной поездки\n\nБезопасность в поездках — приоритет сервиса. Поэтому системы мониторинга в Яндекс Про помогают следить за манерой вождения и соблюдением скоростных ограничений . И только аккуратные водители, которые соблюдают ПДД, продолжат выполнять заказы.\n\nКакое ограничение. За неаккуратное управление автомобилем и превышение скорости водитель потеряет баллы приоритета. Если и после этого нарушения продолжаются, последует отключение от заказов.\n\nПочему пристёгиваться — важно\n\nОтсутствие отдыха\n\nЕсли водитель давно не отдыхал, у него могут ухудшиться реакция и внимательность. И поездка с ним станет небезопасной.\n\nКакое ограничение. Алгоритмы сервиса отслеживают, сколько времени водитель проводит на линии. Как только выяснится, что он давно не делал перерыв, ему придет уведомление в Яндекс Про и рекомендация, когда можно вернуться к заказам. До этого доступ к заказам будет временно ограничен.\n\nОшибки на фотоконтроле\n\nВодителю нужно регулярно проходить фотоконтроль с помощью Яндекс Про. Если все данные машины и документов на фото соответствуют тому, что указано в приложении, доступ к заказам будет открыт или продлён.\n\nРекламные материалы, размещённые на автомобиле, должны соответствовать рекламной политике сервиса . Если реклама не отвечает требованиям, автомобиль не сможет пройти фотоконтроль и другие проверки.\n\nКакое ограничение. Если окажется, что на фото и в приложении информация не совпадает, заказы в Яндекс Про станут временно недоступны. Нужно будет привести всё в порядок и пройти фотоконтроль снова. Чтобы точно устранить недочёты, водителя могут пригласить на стационарный контроль. Однако за умышленную подмену данных доступ к заказам будет ограничен на долгий срок.\n\nКак мы следим за стандартами: фотоконтроль\n\nЗлоупотребление возможностями сервиса\n\nК таким действиям относятся любые попытки в обход правил использовать возможности водительского приложения или попытки обмануть алгоритмы Яндекс Про. Например, когда водитель передает другому человеку учетную запись в Яндекс Про, манипулирует промокодами.\n\nКакое ограничение. За попытку таких действия водитель может сразу получить долгосрочное ограничение.\n\nЕсть нарушения, которые выявляются и подтверждаются не только алгоритмически. В таких случаях помогают свидетельства и отзывы участников поездки и данные от службы поддержки.\n\nКонфликты с пользователями\n\nВо время поездки недопустимы ситуации, которые могут угрожать безопасности пользователя, также под запретом грубость и угрозы. Вот примеры такого поведения:\n\nПопытки удержания пассажиров в автомобиле;\n\nСловесные конфликты с использованием нецензурной лексики и угроз;\n\nПопытки выйти на связь с пассажиром после поездки;\n\nПорча имущества пассажира или попытки присвоить его;\n\nПрименение или угроза применить физическую силу и оружие.\n\nЛюбой чрезвычайной ситуации мы уделяем особое внимание — просим и водителя, и пассажира рассказать, что произошло. Пока не поймём в чём дело, доступ к заказам может быть ограничен.\n\nЧтобы записать любую спорную ситуацию во время заказа, нажмите кнопку « Конфликт » в Яндекс Про. Запись того, что происходило в салоне, поможет разобраться, кто был зачинщиком конфликта.\n\nКакое ограничение . Если выяснится, что водитель затеял конфликт с пользователем, ограничение доступа к сервису будет продлено или станет долгосрочным.\n\nНежелательное поведение\n\nНеуместное внимание во время поездки — запрещено в сервисе. К такому поведению относятся:\n\nНеуместные комплименты, комментарии внешнего вида;\n\nЛюбые прикосновения. Исключение — пользователь с ограниченными возможностями здоровья, который попросил помочь ему добраться до машины или разместиться в салоне;\n\nНавязчивые попытки завязать знакомство;\n\nНепристойные намёки;\n\nНетактичные вопросы — например, про семейное положение или статус в отношениях.\n\nКакое ограничение . За такие действия водитель может получить долгосрочное ограничение доступа к сервису.\n\nО комфортном и безопасном общении в поездке\n\nОпасное поведение во время поездок\n\nСитуации и факторы, которые могут создавать опасность для пассажира — недопустимы во время поездки. Сюда относятся:\n\nСерьезные неисправности автомобиля, которые не устранены после жалоб пользователя и замечаний со стороны сервиса — например, стойкий запах газа в автомобиле с газобалонным оборудованием;\n\nУправление автомобилем в состоянии усталости;\n\nСоздание конфликтов на дороге и нарушение правил ПДД;\n\nОставление пассажира в опасном месте, отличном от пункта назначения. Также недопустимо, чтобы в автомобиле при выполнении заказа были посторонние люди — кроме водителя и пассажиров.\n\nКакое ограничение . После жалобы на такое нарушение доступ к сервису будет приостановлен до выяснения всех обстоятельств. Если нарушение подтвердится — ограничение станет долгосрочным.\n\nКак можно пересмотреть ограничения\n\nЕсли потеряли баллы приоритета\n\nЧтобы вернуть потерянные баллы приоритета, достаточно следовать рекомендациям сервиса. Например, если баллы снижены за неправильный брендинг, нужно привести в порядок оклейку. Как только фотоконтроль подтвердит, что оклейка сделана по стандарту, приоритет вернется.\n\nЕсли ограничение краткосрочное — до полугода\n\nТакое ограничение снимается автоматически, как только его срок заканчивается.\n\nВ некоторых случаях поддержка может самостоятельно уточнить обстоятельства и восстановить доступ к заказам. Если поддержка не примет решение о восстановлении доступа, водитель может заполнить заявку в отдел проверки ограничений — форма будет в сообщении от поддержки. Это актуально для ограничений доступа дольше 24 часов.\n\nПоддержка не снимает ограничения, которые вынесены за регулярные и повторяющиеся нарушения стандартов сервиса и повторяющиеся жалобы пользователей — например, на грубость водителя.\n\nЕсли ограничение долгосрочное — более полугода\n\nЕсли отдел проверки ограничений не готов восстановить доступ, вы можете обратиться в группу разбора. Ссылку на форму для обращения вам отправят на ту почту, которую вы указали при составлении заявки в отдел проверки ограничений. В обращении необходимо предоставить полную информацию о ситуации и ограничении.\n\nНужно подать обращение — его проверит группа разбора, а затем рассмотрит независимый комитет водителей. Он изучит все обстоятельства и порекомендует сервису, как поступить. Подробно об этом читайте в статье по кнопке ниже.\n\nКак отменить долгосрочное ограничение\n\nКак мы следим за стандартами"
}