{
  "url": "https://pro.yandex.com/kz-kk/nur-sultan/knowledge-base/taxi/branding/branding-verification",
  "domain": "pro.yandex.com",
  "locale": "kz-kk",
  "city": "nur-sultan",
  "hreflang": "kk-KZ",
  "category": "branding",
  "slug": "branding-verification",
  "title": "Брендингті қалай растау керек",
  "last_updated": "Соңғы жаңартпа 14 May 2024",
  "breadcrumbs": [
    "Білім базасы",
    "Сапарлар",
    "Брендирование"
  ],
  "content": "Брендингті қалай растау керек\n\nСоңғы жаңартпа 14 May 2024\n\nRU KK\n\nБрендинг артықшылықтары сіз жапсырманы растаған кезде әрекет ете бастайды.\n\nЖапсырманы қалай растау керек\n\nЖапсырманы таққаннан кейін өз таксопаркіңізге хабарласыңыз, олар жүргізушінің карточкасына брендинг туралы белгі қосады.\n\nБіз алдағы брендингті фотобақылау кезінде жапсырманы тексереміз.\n\nБрендинг үшін артықшылықтар жапсырма мен шанақ жарамды екені расталғаннан кейін әрекет ете бастайды.Почему брендирование не подтверждается и что делать.\n\nНеліктен брендинг расталмай жатыр және не істеу керек\n\nСебеп. Сіз фотобақылаудан Яндекс Про-да жапсырма белгіленгенге дейін өткенсіз.\n\nНе істеу керек. Жапсырманы белгілегеніңізді тексеріп, фотобақылаудан қайтадан өтіңіз.\n\nСебеп. Фотобақылау кезінде шанақ немесе жапсырманың күйіне қатысты ескертулер болды.\n\nНе істеу керек. Парақшаңыздағы «Диагностика», «Хабарламалар» бөлімін немесе «Ескертулер» Чатын тексеріңіз. Онда нақты не дұрыс еместігі туралы ескертулер болуы мүмкін. Кемшіліктерді түзетіп, фотобақылаудан қайтадан өтіңіз.\n\nЕгер сізге ескертулер түсініксіз болса немесе кемшіліктерді қалай түзету керектігін білмесеңіз, қолдау қызметіне жазыңыз. Сізге жапсырманы растау үшін не істеу керектігін айтып береді.\n\nБрендингті растауға жиі не кедергі келтіреді\n\nШанақтың күрделі кемшіліктері. Қатты майысқан немесе сызат түскен, бөлшектерінің түстері әр түрлі, лак немесе бояуы түсіп қалған немесе жарылып кеткен автокөліктерге жапсырма тағылмайды.\n\nБөгде жапсырма. Шанақта бөгде жапсырма болмау керек.\n\nБрендинг стандарт бойынша жасалмаған. Сервистің жапсырмасы белгіленген ережелер бойынша жасалуы тиіс.\n\nТакси автокөлігіне қойылған талаптар бұзылған. Әр түрлі аймақтарда билік органдары машиналарға, мысалы, шанақ түсіне қатысты қосымша талаптар қоюы мүмкін.\n\nБрендинг стандарттары\n\nМақала сіз үшін пайдалы болды ма?\n\nИә\n\nЖоқ\n\nКелесі мақала\n\nБрендинг туралы жиі қойылатын сұрақтар"
}