{
  "url": "https://pro.yandex.ru/ru-ru/moskva/knowledge-base/taxi/kiss/doc-in-acc",
  "domain": "pro.yandex.ru",
  "locale": "ru-ru",
  "city": "moskva",
  "hreflang": "ru-RU",
  "category": "kiss",
  "slug": "doc-in-acc",
  "title": "Как загрузить в КИС «АРТ» справку об отсутствии судимости",
  "last_updated": "Последнее обновление 22 нояб 2023",
  "breadcrumbs": [
    "База знаний",
    "Яндекс Такси",
    "Водителям такси о КИС «АРТ»"
  ],
  "content": "Как загрузить в КИС «АРТ» справку об отсутствии судимости\n\nПоследнее обновление 22 нояб 2023\n\nВодителям такси, выполняющим заказы в Москве и Подмосковье, необходимо получить справку из МВД РФ об отсутствии судимости и загрузить её в КИС «АРТ» .\n\nКИС «АРТ» уже начал блокировать аккаунты тех, кто не загрузил справку. С заблокированным аккаунтом доступ к заказам сервиса будет ограничен.\n\nКак подгрузить справку в КИС «АРТ»\n\nВажно! Система принимает только файлы pdf или jpg\n\n1. Зайдите в свой аккаунт в КИС «АРТ »\n\n2. На вкладке «Личные данные» заполните поля для справки, как указано ниже\n\nУкажите дату вашей справки из МВД РФ\n\nЗагрузите файл справки из МВД РФ\n\nГражданам Армении, Беларуси, Казахстана и  Кыргызстана нужно ещё подгрузить справку своего государства. Когда загрузите все нужные вам справки, сохраните изменения\n\nКогда справку проверят, на вкладке появится отметка, у граждан Армении, Беларуси, Казахстана и Кыргызстана будут две такие отметки\n\nЧастые вопросы\n\nКак получить справку гражданам РФ?\n\nНа портале Госуслуг: понадобятся фото или сканы страниц паспорта: главного разворота, данных о прописке и семейном положении.\n\nЗайдите в личный кабинет со своим логином и паролем.\n\nВыберите Услуги → Справки, выписки → Справка об отсутствии судимости. Нажмите «Начать».\n\nВ каком виде нужна справка? — Электронная справка На кого нужна справка? — На меня. Затем нажмите «Перейти к заявлению»\n\nДалее следуйте подсказкам  на сайте.\n\nЧерез МФЦ «Мои документы»\n\nВозьмите паспорт и приходите в ближайший МФЦ «Мои документы» — подайте заявление на получение справки.\n\nСправку могут оформлять до 30 календарных дней при любом способе подачи документов.\n\nКак получить справку?\n\nКак получить справку иностранным гражданам?\n\nПриходите в ближайший МФЦ «Мои документы» или информационный центр МВД по вашему региону. С собой нужно взять документ, удостоверяющий личность, его нотариально заверенный перевод и разрешение на временное пребывание или вид на жительство в России. Подайте заявление на справку — её оформляют в течение 30 календарных дней.\n\nКак получить справку\n\nЗачем нужна справка об отсутствии судимости?\n\nЭто обязательно требование закона о такси, который вступил в силу 1 сентября 2023 года: справку должен получить каждый водитель, который выполняет заказы такси.\n\nГлавное о  новом законе о такси\n\nЧто будет, если не подгрузить справку КИС «АРТ»?\n\nОператоры КИС «АРТ» могут заблокировать ID водителя в системе. С заблокированным ID будет приостановлен доступ к заказам такси — до тех пор, пока не загрузите справку.\n\nСколько есть времени на загрузку справки?\n\nСправку от МВД РФ оформляют в течение 30 дней, поэтому с момента регистрации в сервисе водителю такси с гражданством РФ дается 30 дней на получение справки и её загрузку в КИС «АРТ».\n\nГражданам Армении, Беларуси, Казахстана, Кыргызстана дается 60 дней с момента регистрации в сервисе. Им, помимо справки от МВД РФ, нужно оформить и загрузить в КИС «АРТ» ещё и справку от МВД свой страны.\n\nСправка нужна тем, кто выполняет только доставки через Яндекс Про?\n\nНет, такая справка нужна только водителям такси, которые выполняют поездки с пассажирами.\n\nКак сделать своё фото для аккаунта в КИС «АРТ»"
}